intecomm_form_validators/__init__.py
intecomm_form_validators/apps.py
intecomm_form_validators/constants.py
intecomm_form_validators/urls.py
intecomm_form_validators/utils.py
intecomm_form_validators/consent/__init__.py
intecomm_form_validators/consent/subject_consent_form_validator.py
intecomm_form_validators/prn/__init__.py
intecomm_form_validators/prn/end_of_study.py
intecomm_form_validators/screening/__init__.py
intecomm_form_validators/screening/consent_refusal_form_validator.py
intecomm_form_validators/screening/health_facility_form_validator.py
intecomm_form_validators/screening/health_talk_log_form_validator.py
intecomm_form_validators/screening/patient_call_form_validator.py
intecomm_form_validators/screening/patient_group_form_validator.py
intecomm_form_validators/screening/patient_group_rando_form_validator.py
intecomm_form_validators/screening/patient_log_form_validator.py
intecomm_form_validators/screening/subject_screening_form_validator.py
intecomm_form_validators/subject/__init__.py
intecomm_form_validators/subject/clinical_review_baseline_form_validator.py
intecomm_form_validators/subject/clinical_review_form_validator.py
intecomm_form_validators/subject/complications_baseline_form_validator.py
intecomm_form_validators/subject/complications_followup_form_validator.py
intecomm_form_validators/subject/dm_initial_review_form_validator.py
intecomm_form_validators/subject/dm_medication_adherence_form_validator.py
intecomm_form_validators/subject/dm_review_form_validator.py
intecomm_form_validators/subject/drug_refill_dm_form_validator.py
intecomm_form_validators/subject/drug_refill_hiv_form_validator.py
intecomm_form_validators/subject/drug_refill_htn_form_validator.py
intecomm_form_validators/subject/health_economics_form_validator.py
intecomm_form_validators/subject/hiv_initial_review_form_validator.py
intecomm_form_validators/subject/hiv_medication_adherence_form_validator.py
intecomm_form_validators/subject/hiv_review_form_validator.py
intecomm_form_validators-0.1.55.dist-info/AUTHORS
intecomm_form_validators-0.1.55.dist-info/LICENSE
intecomm_form_validators-0.1.55.dist-info/METADATA
intecomm_form_validators-0.1.55.dist-info/WHEEL
intecomm_form_validators-0.1.55.dist-info/top_level.txt
intecomm_form_validators-0.1.55.dist-info/RECORD
